<?xml version="1.0" encoding="utf-8" ?>
<c2eventsheet>
    <!--All the 'name' attributes are ignored by Construct 2 - they are there for readability only.-->
    <name>Fase Final (Forme-se se for Capaz)</name>
    <events>
        <event-block sid="9765162608650695">
            <conditions>
                <condition id="-2" name="On start of layout" sid="7057668097993137" type="System" />
            </conditions>
            <actions>
                <action id="-4" name="Set position to another object" sid="6921429280797062" type="playerAnim">
                    <param id="0" name="Object">player</param>
                    <param id="1" name="Image point (optional)">0</param>
                </action>
                <action behavior="Pin" id="0" name="Pin to object" sid="2949230539204769" type="playerAnim">
                    <param id="0" name="Pin to">player</param>
                    <param id="1" name="Mode">0</param>
                </action>
                <action id="4" name="Set animation" sid="7649074634257544" type="playerAnim">
                    <param id="0" name="Animation">&quot;Default&quot;</param>
                    <param id="1" name="From">1</param>
                </action>
            </actions>
        </event-block>
        <event-block sid="8935176459426232">
            <conditions>
                <condition id="-1" name="Every tick" sid="4589126109928491" type="System" />
            </conditions>
            <actions>
                <action id="-7" name="Set size" sid="673742081610903" type="player">
                    <param id="0" name="Width">(1-((720-Player.Y)*0.000555))*82</param>
                    <param id="1" name="Height">(1-((720-Player.Y)*0.000555))*144</param>
                </action>
                <action id="-7" name="Set size" sid="3009900728805443" type="playerAnim">
                    <param id="0" name="Width">(1-((720-playerAnim.Y)*0.000555))*82</param>
                    <param id="1" name="Height">(1-((720-playerAnim.Y)*0.000555))*144</param>
                </action>
                <action id="0" name="Set text" sid="9341638240819411" type="pontuacaoTexto">
                    <param id="0" name="Text">&quot;Rendimento acadêmico: &quot; &amp; pontos</param>
                </action>
            </actions>
        </event-block>
        <event-group description="" sid="6751052447410165" title="playerMoveFFFS">
            <sub-events>
                <event-block any="1" sid="2583311756782099">
                    <conditions>
                        <condition id="2" name="Key is down" sid="4369464979036808" type="Keyboard">
                            <param id="0" name="Key">87 (W)</param>
                        </condition>
                        <condition id="2" name="Key is down" sid="7577930988722431" type="Keyboard">
                            <param id="0" name="Key">38 (Up arrow)</param>
                        </condition>
                    </conditions>
                    <actions>
                        <action id="7" name="Set mirrored" sid="9137498159548682" type="playerAnim">
                            <param id="0" name="State">1</param>
                        </action>
                        <action behavior="8Direction" id="7" name="Simulate control" sid="2204283161784401" type="player">
                            <param id="0" name="Control">2</param>
                        </action>
                        <action id="4" name="Set animation" sid="3066358439289303" type="playerAnim">
                            <param id="0" name="Animation">&quot;TrasAndando&quot;</param>
                            <param id="1" name="From">1</param>
                        </action>
                    </actions>
                </event-block>
                <event-block any="1" sid="4354240999080201">
                    <conditions>
                        <condition id="2" name="Key is down" sid="7811947035094138" type="Keyboard">
                            <param id="0" name="Key">65 (A)</param>
                        </condition>
                        <condition id="2" name="Key is down" sid="3028341627734656" type="Keyboard">
                            <param id="0" name="Key">37 (Left arrow)</param>
                        </condition>
                    </conditions>
                    <actions>
                        <action id="7" name="Set mirrored" sid="9849123619027557" type="playerAnim">
                            <param id="0" name="State">0</param>
                        </action>
                        <action behavior="8Direction" id="7" name="Simulate control" sid="7145886402395038" type="player">
                            <param id="0" name="Control">0</param>
                        </action>
                        <action id="4" name="Set animation" sid="8178867767154846" type="playerAnim">
                            <param id="0" name="Animation">&quot;LadoAndando&quot;</param>
                            <param id="1" name="From">1</param>
                        </action>
                    </actions>
                </event-block>
                <event-block any="1" sid="2189815775495272">
                    <conditions>
                        <condition id="2" name="Key is down" sid="9702881740506529" type="Keyboard">
                            <param id="0" name="Key">68 (D)</param>
                        </condition>
                        <condition id="2" name="Key is down" sid="8420555250430538" type="Keyboard">
                            <param id="0" name="Key">39 (Right arrow)</param>
                        </condition>
                    </conditions>
                    <actions>
                        <action id="7" name="Set mirrored" sid="9070042337025009" type="playerAnim">
                            <param id="0" name="State">1</param>
                        </action>
                        <action behavior="8Direction" id="7" name="Simulate control" sid="1822176199420059" type="player">
                            <param id="0" name="Control">1</param>
                        </action>
                        <action id="4" name="Set animation" sid="4007720476374855" type="playerAnim">
                            <param id="0" name="Animation">&quot;LadoAndando&quot;</param>
                            <param id="1" name="From">1</param>
                        </action>
                    </actions>
                </event-block>
                <event-block any="1" sid="259763088041246">
                    <conditions>
                        <condition id="2" name="Key is down" sid="1781227584301451" type="Keyboard">
                            <param id="0" name="Key">83 (S)</param>
                        </condition>
                        <condition id="2" name="Key is down" sid="9995782970026461" type="Keyboard">
                            <param id="0" name="Key">40 (Down arrow)</param>
                        </condition>
                    </conditions>
                    <actions>
                        <action id="7" name="Set mirrored" sid="5860999201973957" type="playerAnim">
                            <param id="0" name="State">1</param>
                        </action>
                        <action behavior="8Direction" id="7" name="Simulate control" sid="1318105454922122" type="player">
                            <param id="0" name="Control">3</param>
                        </action>
                        <action id="4" name="Set animation" sid="2179193773821538" type="playerAnim">
                            <param id="0" name="Animation">&quot;FrenteAndando&quot;</param>
                            <param id="1" name="From">1</param>
                        </action>
                    </actions>
                </event-block>
                <event-block sid="7919200414995156">
                    <conditions>
                        <condition id="2" name="Key is down" sid="4005480434035672" type="Keyboard">
                            <param id="0" name="Key">87 (W)</param>
                        </condition>
                        <condition id="2" name="Key is down" sid="7325460842124629" type="Keyboard">
                            <param id="0" name="Key">83 (S)</param>
                        </condition>
                    </conditions>
                    <actions>
                        <action id="4" name="Set animation" sid="5639464411243017" type="playerAnim">
                            <param id="0" name="Animation">&quot;FrenteParado&quot;</param>
                            <param id="1" name="From">1</param>
                        </action>
                    </actions>
                </event-block>
                <event-block sid="7696280092630503">
                    <conditions>
                        <condition id="2" name="Key is down" sid="2942249165460636" type="Keyboard">
                            <param id="0" name="Key">65 (A)</param>
                        </condition>
                        <condition id="2" name="Key is down" sid="9039572321011582" type="Keyboard">
                            <param id="0" name="Key">68 (D)</param>
                        </condition>
                    </conditions>
                    <actions>
                        <action id="4" name="Set animation" sid="6219312602426583" type="playerAnim">
                            <param id="0" name="Animation">&quot;FrenteParado&quot;</param>
                            <param id="1" name="From">1</param>
                        </action>
                    </actions>
                </event-block>
                <event-block sid="7808754473495884">
                    <conditions>
                        <condition id="2" name="Key is down" sid="2579518602560079" type="Keyboard">
                            <param id="0" name="Key">38 (Up arrow)</param>
                        </condition>
                        <condition id="2" name="Key is down" sid="5618375392231702" type="Keyboard">
                            <param id="0" name="Key">40 (Down arrow)</param>
                        </condition>
                    </conditions>
                    <actions>
                        <action id="4" name="Set animation" sid="2775325661499118" type="playerAnim">
                            <param id="0" name="Animation">&quot;FrenteParado&quot;</param>
                            <param id="1" name="From">1</param>
                        </action>
                    </actions>
                </event-block>
                <event-block sid="2751764296564113">
                    <conditions>
                        <condition id="2" name="Key is down" sid="7382471784497499" type="Keyboard">
                            <param id="0" name="Key">37 (Left arrow)</param>
                        </condition>
                        <condition id="2" name="Key is down" sid="5613393681707267" type="Keyboard">
                            <param id="0" name="Key">39 (Right arrow)</param>
                        </condition>
                    </conditions>
                    <actions>
                        <action id="4" name="Set animation" sid="6671574924110977" type="playerAnim">
                            <param id="0" name="Animation">&quot;FrenteParado&quot;</param>
                            <param id="1" name="From">1</param>
                        </action>
                    </actions>
                </event-block>
                <event-block any="1" sid="3773383549790542">
                    <conditions>
                        <condition id="3" name="On key released" sid="8791430302761867" type="Keyboard">
                            <param id="0" name="Key">87 (W)</param>
                        </condition>
                        <condition id="3" name="On key released" sid="931663926412571" type="Keyboard">
                            <param id="0" name="Key">38 (Up arrow)</param>
                        </condition>
                    </conditions>
                    <actions>
                        <action id="4" name="Set animation" sid="1766117261780943" type="playerAnim">
                            <param id="0" name="Animation">&quot;TrasParado&quot;</param>
                            <param id="1" name="From">1</param>
                        </action>
                    </actions>
                </event-block>
                <event-block any="1" sid="3255248241284806">
                    <conditions>
                        <condition id="3" name="On key released" sid="7540209602363084" type="Keyboard">
                            <param id="0" name="Key">83 (S)</param>
                        </condition>
                        <condition id="3" name="On key released" sid="176583741807398" type="Keyboard">
                            <param id="0" name="Key">40 (Down arrow)</param>
                        </condition>
                    </conditions>
                    <actions>
                        <action id="4" name="Set animation" sid="3151753962808145" type="playerAnim">
                            <param id="0" name="Animation">&quot;FrenteParado&quot;</param>
                            <param id="1" name="From">1</param>
                        </action>
                    </actions>
                </event-block>
                <event-block any="1" sid="242006943993595">
                    <conditions>
                        <condition id="3" name="On key released" sid="8621783547556311" type="Keyboard">
                            <param id="0" name="Key">65 (A)</param>
                        </condition>
                        <condition id="3" name="On key released" sid="4972796537701502" type="Keyboard">
                            <param id="0" name="Key">37 (Left arrow)</param>
                        </condition>
                    </conditions>
                    <actions>
                        <action id="4" name="Set animation" sid="3633798121633091" type="playerAnim">
                            <param id="0" name="Animation">&quot;EsquerdaParado&quot;</param>
                            <param id="1" name="From">1</param>
                        </action>
                    </actions>
                </event-block>
                <event-block any="1" sid="5105599929156162">
                    <conditions>
                        <condition id="3" name="On key released" sid="7372659682479313" type="Keyboard">
                            <param id="0" name="Key">68 (D)</param>
                        </condition>
                        <condition id="3" name="On key released" sid="2130030036468228" type="Keyboard">
                            <param id="0" name="Key">39 (Right arrow)</param>
                        </condition>
                    </conditions>
                    <actions>
                        <action id="4" name="Set animation" sid="8585015241693119" type="playerAnim">
                            <param id="0" name="Animation">&quot;DireitaParado&quot;</param>
                            <param id="1" name="From">1</param>
                        </action>
                    </actions>
                </event-block>
            </sub-events>
        </event-group>
        <event-block sid="4465934341037544">
            <conditions>
                <condition id="0" name="On key pressed" sid="9637123849405706" type="Keyboard">
                    <param id="0" name="Key">90 (Z)</param>
                </condition>
            </conditions>
            <actions>
                <action id="-36" name="Save" sid="1565888738504929" type="System">
                    <param id="0" name="Slot">&quot;save&quot;</param>
                </action>
            </actions>
        </event-block>
        <event-block sid="7044295167826837">
            <conditions>
                <condition id="0" name="On key pressed" sid="2168768331416239" type="Keyboard">
                    <param id="0" name="Key">76 (L)</param>
                </condition>
            </conditions>
            <actions>
                <action id="-37" name="Load" sid="7590686521419319" type="System">
                    <param id="0" name="Slot">&quot;save&quot;</param>
                </action>
            </actions>
        </event-block>
    </events>
</c2eventsheet>
